[ {
  "id" : 200001,
  "stack" : 999,
  "quality" : 0,
  "effect" : 0,
  "effectParam" : ""
}, {
  "id" : 200002,
  "stack" : 999,
  "quality" : 0,
  "effect" : 0,
  "effectParam" : ""
}, {
  "id" : 201003,
  "stack" : 1,
  "quality" : 0,
  "effect" : 0,
  "effectParam" : ""
}, {
  "id" : 201004,
  "stack" : 1,
  "quality" : 0,
  "effect" : 0,
  "effectParam" : ""
}, {
  "id" : 201005,
  "stack" : 1,
  "quality" : 0,
  "effect" : 0,
  "effectParam" : ""
}, {
  "id" : 201006,
  "stack" : 1,
  "quality" : 0,
  "effect" : 0,
  "effectParam" : ""
}, {
  "id" : 202001,
  "stack" : 1,
  "quality" : 0,
  "effect" : 0,
  "effectParam" : ""
}, {
  "id" : 202002,
  "stack" : 1,
  "quality" : 0,
  "effect" : 0,
  "effectParam" : ""
} ]